oflibpytorch/__init__.py
oflibpytorch/flow_class.py
oflibpytorch/flow_operations.py
oflibpytorch/utils.py
oflibpytorch-2.1.1.dist-info/LICENSE.txt
oflibpytorch-2.1.1.dist-info/METADATA
oflibpytorch-2.1.1.dist-info/WHEEL
oflibpytorch-2.1.1.dist-info/top_level.txt
oflibpytorch-2.1.1.dist-info/RECORD
