Metadata-Version: 2.1
Name: oflibpytorch
Version: 2.1.1
Summary: Differentiable optical flow library using a custom flow class based on PyTorch tensors
Home-page: https://github.com/RViMLab/oflibpytorch
Author: Claudio S. Ravasio
Author-email: claudio.s.ravasio@gmail.com
License: MIT
Project-URL: Documentation, https://oflibpytorch.rtfd.io
Project-URL: Source, https://github.com/RViMLab/oflibpytorch
Project-URL: Tracker, https://github.com/RViMLab/oflibpytorch/issues
Keywords: optical flow,flow,flow field,flow composition,flow combination,flow visualisation
Platform: UNKNOWN
Classifier: Development Status :: 5 - Production/Stable
Classifier: License :: OSI Approved :: MIT License
Classifier: Programming Language :: Python :: 3
Requires-Python: >=3.7
Requires-Dist: numpy
Requires-Dist: opencv-python
Requires-Dist: scipy
